wize/WIZE.py
wize/__init__.py
wize-0.3.7.dist-info/LICENCE
wize-0.3.7.dist-info/METADATA
wize-0.3.7.dist-info/WHEEL
wize-0.3.7.dist-info/entry_points.txt
wize-0.3.7.dist-info/top_level.txt
wize-0.3.7.dist-info/RECORD
