Metadata-Version: 2.1
Name: wize
Version: 0.3.7
Summary: Module specialising in everything...
Home-page: https://github.com/Cu3t0m/wize
Author: Diwan Mohamed Faheer
Author-email: diwanmohamedfaheer@gmail.com
License: UNKNOWN
Platform: UNKNOWN
Classifier: Programming Language :: Python :: 3
Classifier: License :: OSI Approved :: MIT License
Classifier: Operating System :: OS Independent
License-File: LICENCE
Requires-Dist: colored (==1.4.3)
